{
     "id": 34,
     "url": "/api/v2/role_team_assignments/34/",
     "summary_fields": {
          "created_by": {
               "id": 1,
               "username": "admin",
               "first_name": "",
               "last_name": ""
          },
          "role_definition": {
               "id": 35,
               "name": "JobTemplate Read Compat",
               "description": "Has Read permission to JobTemplate for backwards API compatibility",
               "managed": false
          },
          "team": {
               "id": 2,
               "name": "App Team",
               "description": ""
          },
          "content_object": {
               "id": 32,
               "name": "100.1 Download Agents",
               "description": ""
          }
     },
     "created": "2024-08-07T11:28:40.977483Z",
     "created_by": 1,
     "content_type": "awx.jobtemplate",
     "object_id": "32",
     "object_ansible_id": null,
     "role_definition": 35,
     "team": 2
}
